bails_aws_utils/__init__.py
bails_aws_utils/misc/__init__.py
bails_aws_utils/misc/cron_helper.py
bails_aws_utils/misc/log_helper.py
bails_aws_utils/route53/__init__.py
bails_aws_utils/route53/dynamic_dns_tool.py
bails_aws_utils/route53/gmail.py
bails_aws_utils/route53/utils.py
bails_aws_utils-0.2.0.data/scripts/dynamic-dns
bails_aws_utils-0.2.0.data/scripts/gmail-mx-create
bails_aws_utils-0.2.0.dist-info/METADATA
bails_aws_utils-0.2.0.dist-info/WHEEL
bails_aws_utils-0.2.0.dist-info/top_level.txt
bails_aws_utils-0.2.0.dist-info/RECORD
