Metadata-Version: 2.1
Name: bails-aws-utils
Version: 0.2.0
Summary: For making AWS easier
Home-page: https://github.com/beverts312/bails-aws-utils
Author: Bailey Everts
Author-email: me@baileyeverts.net
License: MIT
Platform: UNKNOWN
Requires-Dist: boto3
Requires-Dist: python-crontab
Requires-Dist: requests
